react_agent_compensation/__init__.py
react_agent_compensation/core/__init__.py
react_agent_compensation/core/config.py
react_agent_compensation/core/exceptions.py
react_agent_compensation/core/models.py
react_agent_compensation/core/protocols.py
react_agent_compensation/core/recovery_manager.py
react_agent_compensation/core/transaction_log.py
react_agent_compensation/core/batch/__init__.py
react_agent_compensation/core/batch/context.py
react_agent_compensation/core/batch/detector.py
react_agent_compensation/core/batch/lock.py
react_agent_compensation/core/batch/manager.py
react_agent_compensation/core/errors/__init__.py
react_agent_compensation/core/errors/base.py
react_agent_compensation/core/errors/composite.py
react_agent_compensation/core/errors/content.py
react_agent_compensation/core/errors/exception.py
react_agent_compensation/core/errors/explicit.py
react_agent_compensation/core/errors/permanent.py
react_agent_compensation/core/extraction/__init__.py
react_agent_compensation/core/extraction/base.py
react_agent_compensation/core/extraction/composite.py
react_agent_compensation/core/extraction/heuristic.py
react_agent_compensation/core/extraction/passthrough.py
react_agent_compensation/core/extraction/path_resolver.py
react_agent_compensation/core/extraction/recursive.py
react_agent_compensation/core/extraction/schema.py
react_agent_compensation/core/extraction/state_mappers.py
react_agent_compensation/core/mcp/__init__.py
react_agent_compensation/core/mcp/client.py
react_agent_compensation/core/mcp/parser.py
react_agent_compensation/core/mcp/tools.py
react_agent_compensation/core/retry/__init__.py
react_agent_compensation/core/retry/base.py
react_agent_compensation/core/retry/exponential.py
react_agent_compensation/core/retry/no_retry.py
react_agent_compensation/langchain_adaptor/__init__.py
react_agent_compensation/langchain_adaptor/adapters.py
react_agent_compensation/langchain_adaptor/agent.py
react_agent_compensation/langchain_adaptor/interceptors.py
react_agent_compensation-0.2.0.dist-info/METADATA
react_agent_compensation-0.2.0.dist-info/WHEEL
react_agent_compensation-0.2.0.dist-info/RECORD
