Metadata-Version: 2.4
Name: react-agent-compensation
Version: 0.2.0
Summary: Framework-agnostic compensation/rollback library for ReAct agents
Project-URL: Homepage, https://github.com/Kavirubc/react-agent-compensation
Project-URL: Repository, https://github.com/Kavirubc/react-agent-compensation
Author: Kaviru Hapuarachchi
License-Expression: MIT
Keywords: agents,compensation,langchain,llm,react-agent,recovery,rollback
Classifier: Development Status :: 4 - Beta
Classifier: Intended Audience :: Developers
Classifier: License :: OSI Approved :: MIT License
Classifier: Programming Language :: Python :: 3
Classifier: Programming Language :: Python :: 3.10
Classifier: Programming Language :: Python :: 3.11
Classifier: Programming Language :: Python :: 3.12
Classifier: Topic :: Software Development :: Libraries :: Python Modules
Requires-Python: >=3.10
Requires-Dist: pydantic>=2.0
Provides-Extra: all
Requires-Dist: anthropic>=0.20.0; extra == 'all'
Requires-Dist: fastmcp>=2.0.0; extra == 'all'
Requires-Dist: langchain-google-genai>=2.0.0; extra == 'all'
Requires-Dist: langchain-mcp-adapters>=0.1.0; extra == 'all'
Requires-Dist: langchain>=0.3.0; extra == 'all'
Requires-Dist: langgraph>=0.2.0; extra == 'all'
Requires-Dist: langsmith>=0.1.0; extra == 'all'
Requires-Dist: mcp>=1.0.0; extra == 'all'
Requires-Dist: mypy>=1.0; extra == 'all'
Requires-Dist: openai>=1.0.0; extra == 'all'
Requires-Dist: pymongo>=4.0.0; extra == 'all'
Requires-Dist: pytest-asyncio>=0.21.0; extra == 'all'
Requires-Dist: pytest-cov>=4.0; extra == 'all'
Requires-Dist: pytest>=7.0; extra == 'all'
Requires-Dist: python-dotenv>=1.0.0; extra == 'all'
Requires-Dist: ruff>=0.1.0; extra == 'all'
Provides-Extra: dev
Requires-Dist: mypy>=1.0; extra == 'dev'
Requires-Dist: pytest-asyncio>=0.21.0; extra == 'dev'
Requires-Dist: pytest-cov>=4.0; extra == 'dev'
Requires-Dist: pytest>=7.0; extra == 'dev'
Requires-Dist: ruff>=0.1.0; extra == 'dev'
Provides-Extra: examples
Requires-Dist: langchain-google-genai>=2.0.0; extra == 'examples'
Requires-Dist: langsmith>=0.1.0; extra == 'examples'
Requires-Dist: pymongo>=4.0.0; extra == 'examples'
Requires-Dist: python-dotenv>=1.0.0; extra == 'examples'
Provides-Extra: langchain
Requires-Dist: langchain>=0.3.0; extra == 'langchain'
Requires-Dist: langgraph>=0.2.0; extra == 'langchain'
Provides-Extra: llm
Requires-Dist: anthropic>=0.20.0; extra == 'llm'
Requires-Dist: openai>=1.0.0; extra == 'llm'
Provides-Extra: mcp
Requires-Dist: fastmcp>=2.0.0; extra == 'mcp'
Requires-Dist: langchain-mcp-adapters>=0.1.0; extra == 'mcp'
Requires-Dist: mcp>=1.0.0; extra == 'mcp'
